fluctlight/__init__.py
fluctlight/greet.py
fluctlight.ai-0.0.1.dist-info/METADATA
fluctlight.ai-0.0.1.dist-info/WHEEL
fluctlight.ai-0.0.1.dist-info/top_level.txt
fluctlight.ai-0.0.1.dist-info/RECORD
